Metadata-Version: 2.1
Name: visum-io-sdk
Version: 1.0.4
Summary: Python client for visum.io public API
Home-page: https://demo.visum.io
License: MIT
Platform: UNKNOWN
